rios.core-0.10.0-py3.9-nspkg.pth
rios/core/__init__.py
rios/core/scripts.py
rios/core/output/__init__.py
rios/core/output/assessment.py
rios/core/output/calculationset.py
rios/core/output/common.py
rios/core/output/form.py
rios/core/output/instrument.py
rios/core/output/interaction.py
rios/core/validation/__init__.py
rios/core/validation/assessment.py
rios/core/validation/calculationset.py
rios/core/validation/common.py
rios/core/validation/form.py
rios/core/validation/instrument.py
rios/core/validation/interaction.py
rios.core-0.10.0.dist-info/LICENSE.rst
rios.core-0.10.0.dist-info/METADATA
rios.core-0.10.0.dist-info/NOTICE
rios.core-0.10.0.dist-info/WHEEL
rios.core-0.10.0.dist-info/entry_points.txt
rios.core-0.10.0.dist-info/namespace_packages.txt
rios.core-0.10.0.dist-info/top_level.txt
rios.core-0.10.0.dist-info/zip-safe
rios.core-0.10.0.dist-info/RECORD
