Metadata-Version: 2.2
Name: rios.core
Version: 0.10.0
Summary: Parsing and Validation Library for RIOS Files
Home-page: https://github.com/prometheusresearch/rios.core
Author: Prometheus Research, LLC
Author-email: contact@prometheusresearch.com
License: Apache-2.0
Keywords: rios prismh research instrument assessment standard validation
Classifier: Intended Audience :: Developers
Classifier: License :: OSI Approved :: Apache Software License
Classifier: Programming Language :: Python :: 2.7
Classifier: Programming Language :: Python :: 3.5
Classifier: Programming Language :: Python :: 3.6
Classifier: Programming Language :: Python :: 3.7
Classifier: Programming Language :: Python :: 3.8
License-File: LICENSE.rst
License-File: NOTICE
Requires-Dist: six
Requires-Dist: colander<2,>=1
Requires-Dist: pyyaml
Dynamic: author
Dynamic: author-email
Dynamic: classifier
Dynamic: description
Dynamic: home-page
Dynamic: keywords
Dynamic: license
Dynamic: requires-dist
Dynamic: summary
